sco_engine-0.3.1.dist-info/DESCRIPTION.rst
sco_engine-0.3.1.dist-info/METADATA
sco_engine-0.3.1.dist-info/RECORD
sco_engine-0.3.1.dist-info/WHEEL
sco_engine-0.3.1.dist-info/metadata.json
sco_engine-0.3.1.dist-info/top_level.txt
scoengine/__init__.py
scoengine/export_sco_parameters.py
scoengine/model.py
scoengine/reqbuf_worker.py
