Metadata-Version: 2.0
Name: sco-engine
Version: 0.3.1
Summary: Library to run predictive models for experiments that are defined in the Standard Cortical Observer Data Store
Home-page: https://github.com/heikomuller/sco-engine
Author: Heiko Mueller
Author-email: heiko.muller@gmail.com
License: GPLv3
Keywords: neuroscience vision cortex
Platform: UNKNOWN
Requires-Dist: pika
Requires-Dist: pyaml
Requires-Dist: pymongo
Requires-Dist: sco-datastore
